{
"Package":{'package="com.mktsylayo.teyhgn" platformBuildVersionCode="23"'},
"Activities":{'activity android:excludeFromRecents="true" android:label="@string/app_name" android:name="com.mktsylayo.teyhgn.MainActivity" ', 'activity android:label="akdbyc" ', 'activity android:label="jgxdtj" ', 'activity android:label="ufjzozrhcf" ', 'activity android:excludeFromRecents="true" android:name="com.mktsylayo.teyhgn.osphtmi" ', 'activity android:configChanges="keyboardHidden|orientation|screenSize" android:excludeFromRecents="true" android:label="" android:launchMode="singleTop" android:name="com.mktsylayo.teyhgn.cjeyr" android:theme="@style/AppMainTheme" ', 'activity android:label="lywtsecr" ', 'activity android:label="vjzgbwvso"', 'activity android:label="jhpgknha" ', 'activity android:label="bpxkocpzt" ', 'activity android:label="tgmipvym" ', 'activity android:configChanges="keyboardHidden|orientation|screenSize" android:excludeFromRecents="true" android:label="" android:launchMode="singleTop" android:name="com.mktsylayo.teyhgn.fqkukom" android:theme="@style/AppDialog" '},
"Services":{'service android:name="com.mktsylayo.teyhgn.cdgxig"', 'service android:label="System Process" android:name="com.mktsylayo.teyhgn.bugvduf"', 'service android:enabled="true" android:name="com.mktsylayo.teyhgn.gvuca"', 'service android:name="com.mktsylayo.teyhgn.xvnialqiq"', 'service android:name="com.mktsylayo.teyhgn.avbukf"'},
"Providers":{''},
"Receivers":{'receiver android:enabled="true" android:name="com.mktsylayo.teyhgn.tswtvdj" android:permission="android.permission.BROADCAST_SMS"', 'receiver android:name="com.mktsylayo.teyhgn.usxswnkm"', 'receiver android:description="@string/admin_description" android:enabled="true" android:name="com.mktsylayo.teyhgn.vbagfcs" android:permission="android.permission.BIND_DEVICE_ADMIN"', 'receiver android:name="com.mktsylayo.teyhgn.iyzquk"', 'receiver android:exported="false" android:name="com.mktsylayo.teyhgn.ndjnuky"'},
"Intents Action":{'action android:name="android.app.action.DEVICE_ADMIN_ENABLED"', 'action android:name="android.app.action.ACTION_DEVICE_ADMIN_DISABLE_REQUESTED"', 'action android:name="android.provider.Telephony.SMS_DELIVER"', 'action android:name="android.intent.action.MAIN"', 'action android:name="android.provider.Telephony.SMS_RECEIVED"', 'action android:name="android.provider.Telephony.SMS_SENT"', 'action android:name="com.som"', 'action android:name="android.intent.action.REBOOT"', 'action android:name="android.send.mms"', 'action android:name="android.intent.action.BOOT_COMPLETED"', 'action android:name="android.app.action.DEVICE_ADMIN_DISABLED"', 'action android:name="android.intent.action.QUICKBOOT_POWERON"'},
"Intents Category":{'category android:name="android.intent.category.LAUNCHER"'},
"Permissions":{'permission android:name="android.permission.GET_TASKS"', 'permission android:name="android.permission.READ_CALL_LOG"', 'permission android:name="android.permission.READ_PHONE_STATE"', 'permission android:name="com.sec.android.app.sbrowser.operatorbookmarks.permission.READ_HISTORY_BOOKMARKS"', 'permission android:name="com.android.browser.permission.READ_HISTORY_BOOKMARKS"', 'permission android:name="android.permission.WRITE_EXTERNAL_STORAGE"', 'permission android:name="android.permission.SYSTEM_ALERT_WINDOW"', 'permission android:name="android.permission.WRITE_SMS"', 'permission android:name="android.permission.RECEIVE_BOOT_COMPLETED"', 'permission android:name="android.permission.CHANGE_NETWORK_STATE"', 'permission android:name="android.permission.ACCESS_NETWORK_STATE"', 'permission android:name="android.permission.WRITE_SETTINGS"', 'permission="android.permission.BROADCAST_SMS"', 'permission android:name="android.permission.DISABLE_KEYGUARD"', 'permission android:name="android.permission.RECEIVE_SMS"', 'permission android:name="android.permission.INTERNET"', 'permission android:name="android.permission.SEND_SMS"', 'permission android:name="android.permission.CHANGE_WIFI_STATE"', 'permission android:name="android.permission.BROADCAST_PACKAGE_ADDED"', 'permission android:name="android.permission.ACCESS_WIFI_STATE"', 'permission android:name="android.permission.WAKE_LOCK"', 'permission android:name="android.permission.READ_CONTACTS"', 'permission android:name="android.permission.USE_CREDENTIALS"', 'permission android:name="android.permission.READ_SMS"', 'permission="android.permission.BIND_DEVICE_ADMIN"'},
"Exported":{''},
"Backup":{'allowBackup="true" android:icon="@drawable/ic_launcher" android:label="@string/app_name" android:name="com.dswkgs.asyelsue.dcpbrsie"'},
"Meta-Data":{'meta-data android:name="preventRestart" android:value="true"', 'meta-data android:name="android.app.device_admin" android:resource="@xml/empty"', 'meta-data android:name="stopOnDeviceLock" android:value="false"'},
"Uses-Features":{''},
"Number of Icons":{'6'},
"Number of Pictures":{'0'},
"Number of Audio":{'0'},
"Number of Videos":{'0'},
"Size of the App":{'1000K'},
"lockDetected":True,
"lockStrategy":DrawOver,
"textDetected":False,
"textScore":0,
"languages":['english'],
"hasRWPermission":True,
"encryptionDetected":False,
"photoCaptureDetected":False,
"deviceAdminUsed":True,
"deviceAdminPolicies":[],
"fromReflection":False,
"textComment":Threat: 0.174078, Porn: 0.316228, Law: 0.000000, Copyright: 0.198680, Moneypak: 0.000000,
"suspiciousFiles":{copyright=[res/values/strings.xml], law=[], moneypak=[], threat=[res/values/strings.xml], porn=[res/values/strings.xml]},
}